mathematic_delon
