Metadata-Version: 2.1
Name: mathematic-package-aircooled18
Version: 1.1.0
Summary: Matematika untuk Python
Home-page: https://github.com/pypa/sampleproject
Author: Delon Arihta Cendana
Author-email: delonarihta@gmail.com
License: UNKNOWN
Project-URL: Bug Tracker, https://github.com/pypa/sampleproject/issues
Platform: UNKNOWN
Classifier: Programming Language :: Python :: 3
Classifier: License :: OSI Approved :: MIT License
Classifier: Operating System :: OS Independent
Requires-Python: >=3.6
License-File: LICENSE
